{
  "name": "google-cloud-auth",
  "slug": "google-cloud-auth",
  "source": "claudskills",
  "source_url": "https://claudskills.com/skills/google-cloud-auth/",
  "download_url": "https://claudskills.com/skills/google-cloud-auth/SKILL.md",
  "external_source_url": "",
  "license": "MIT",
  "description": "Provides expert guidance on authenticating and authorizing to Google Cloud services and APIs, covering human users, service identities, Application Default Credentials (ADC), and best practices for secure access.",
  "category": "security",
  "download_status": "downloaded",
  "download_note": "cached",
  "metadata": {
    "subcategory": "security-misc",
    "featured": false
  },
  "collected_at": "2026-05-27T03:43:08+00:00"
}
