{
  "name": "detecting-shadow-it-cloud-usage",
  "slug": "detecting-shadow-it-cloud-usage",
  "source": "claudskills",
  "source_url": "https://claudskills.com/skills/detecting-shadow-it-cloud-usage/",
  "download_url": "https://claudskills.com/skills/detecting-shadow-it-cloud-usage/SKILL.md",
  "external_source_url": "",
  "license": "Apache-2.0",
  "description": "Detect unauthorized SaaS and cloud service usage (shadow IT) by analyzing proxy logs, DNS query logs, and netflow",
  "category": "general",
  "download_status": "downloaded",
  "download_note": "cached",
  "metadata": {
    "subcategory": "general-misc",
    "featured": false
  },
  "collected_at": "2026-05-27T03:42:40+00:00"
}
