{
  "name": "production-budgeting",
  "slug": "production-budgeting",
  "source": "claudskills",
  "source_url": "https://claudskills.com/skills/production-budgeting/",
  "download_url": "https://claudskills.com/skills/production-budgeting/SKILL.md",
  "external_source_url": "",
  "license": "",
  "description": "Audit film, television, and digital content production budgets for above-the-line (ATL) and below-the-line (BTL) cost accuracy, SAG-AFTRA/DGA/WGA/IATSE union rate compliance, fringe and payroll tax calculations, VFX bid variance analysis, post-production cost validation, completion bond readiness, EFC (Estimated Final Cost) projections, tax incentive qualification tracking, and financing waterfall alignment using Movie Magic Budgeting, Hot Budget, or EP formats.",
  "category": "general",
  "download_status": "downloaded",
  "download_note": "cached",
  "metadata": {
    "subcategory": "business-ops",
    "featured": false
  },
  "collected_at": "2026-05-27T03:43:59+00:00"
}
