{
  "name": "ts-implement",
  "slug": "ts-implement",
  "source": "claudskills",
  "source_url": "https://claudskills.com/skills/ts-implement/",
  "download_url": "https://claudskills.com/skills/ts-implement/SKILL.md",
  "external_source_url": "",
  "license": "",
  "description": "TypeScript実装のベストプラクティスとコーディング規約。型安全なコード、モダンな機能、エラーハンドリング、品質基準を提供。TypeScript実装、コーディング規約、型定義パターンが必要な時に参照。",
  "category": "engineering",
  "download_status": "downloaded",
  "download_note": "cached",
  "metadata": {
    "subcategory": "engineering-misc",
    "featured": false
  },
  "collected_at": "2026-05-27T03:44:30+00:00"
}
