{
  "name": "binutils",
  "slug": "binutils",
  "source": "claudskills",
  "source_url": "https://claudskills.com/skills/binutils/",
  "download_url": "https://claudskills.com/skills/binutils/SKILL.md",
  "external_source_url": "",
  "license": "",
  "description": "GNU binutils skill for binary manipulation and analysis. Use when using ar for static libraries, strip or objcopy for binary processing, addr2line for converting addresses to source locations, strings for text extraction, or c++filt for C++ name demangling. Activates on queries about ar, strip, objcopy, addr2line, strings, c++filt, ranlib, or binary post-processing tasks.",
  "category": "general",
  "download_status": "downloaded",
  "download_note": "cached",
  "metadata": {
    "subcategory": "general-misc",
    "featured": false
  },
  "collected_at": "2026-05-27T03:42:06+00:00"
}
