{
  "name": "bicep",
  "slug": "bicep",
  "source": "claudskills",
  "source_url": "https://claudskills.com/skills/bicep/",
  "download_url": "https://claudskills.com/skills/bicep/SKILL.md",
  "external_source_url": "",
  "license": "",
  "description": "Expert assistance for Azure Bicep infrastructure-as-code. Provides best practices for authoring Bicep templates, Azure resource type discovery with API versions, resource schema retrieval, and Azure Verified Modules (AVM) guidance. Use when writing Bicep files, deploying Azure resources, looking up resource types/schemas, or working with AVM modules.",
  "category": "engineering",
  "download_status": "downloaded",
  "download_note": "cached",
  "metadata": {
    "subcategory": "engineering-misc",
    "featured": false
  },
  "collected_at": "2026-05-27T03:42:05+00:00"
}
