{
  "name": "himalaya-cli-email-client-imap-smtp-notmuch",
  "slug": "himalaya-cli-email-client-imap-smtp-notmuch",
  "source": "claudskills",
  "source_url": "https://claudskills.com/skills/himalaya-cli-email-client-imap-smtp-notmuch/",
  "download_url": "https://claudskills.com/skills/himalaya-cli-email-client-imap-smtp-notmuch/SKILL.md",
  "external_source_url": "",
  "license": "",
  "description": "Himalaya is a CLI email client written in Rust that supports IMAP, Maildir, and Notmuch backends for reading mail, and SMTP and Sendmail for sending. It features multi-account configuration, PGP encryption, OAuth 2.0, system keyring integration, and JSON output for scripting and agent automation.",
  "category": "tools",
  "download_status": "downloaded",
  "download_note": "cached",
  "metadata": {
    "subcategory": "cli-builders",
    "featured": false
  },
  "collected_at": "2026-05-27T03:43:13+00:00"
}
