{
  "name": "deepgram-security-basics",
  "slug": "deepgram-security-basics",
  "source": "claudskills",
  "source_url": "https://claudskills.com/skills/deepgram-security-basics/",
  "download_url": "https://claudskills.com/skills/deepgram-security-basics/SKILL.md",
  "external_source_url": "",
  "license": "MIT",
  "description": "Apply Deepgram security best practices for API key management and data protection. Use when securing Deepgram integrations, implementing key rotation, or auditing security configurations. Trigger: \"deepgram security\", \"deepgram API key security\", \"secure deepgram\", \"deepgram key rotation\", \"deepgram data protection\", \"deepgram PII redaction\".",
  "category": "security",
  "download_status": "downloaded",
  "download_note": "cached",
  "metadata": {
    "subcategory": "security-misc",
    "featured": false
  },
  "collected_at": "2026-05-27T03:42:37+00:00"
}
