{
  "name": "firestore-security-rules-generation",
  "slug": "firestore-security-rules-generation",
  "source": "claudskills",
  "source_url": "https://claudskills.com/skills/firestore-security-rules-generation/",
  "download_url": "https://claudskills.com/skills/firestore-security-rules-generation/SKILL.md",
  "external_source_url": "",
  "license": "",
  "description": "Firestore Security Rules patterns for user-scoped access, RBAC with custom claims, multi-tenant isolation, field validation, immutable fields, and testing strategies. Includes rules syntax and best practices. Keywords: \"security rules\", \"rbac\", \"multi-tenant\", \"validation\", \"firestore rules\", \"access control\"",
  "category": "security",
  "download_status": "downloaded",
  "download_note": "cached",
  "metadata": {
    "subcategory": "identity-access",
    "featured": false
  },
  "collected_at": "2026-05-27T03:42:58+00:00"
}
