{
  "name": "ai-regulatory-mapper",
  "slug": "ai-regulatory-mapper",
  "source": "claudskills",
  "source_url": "https://claudskills.com/skills/ai-regulatory-mapper/",
  "download_url": "https://claudskills.com/skills/ai-regulatory-mapper/SKILL.md",
  "external_source_url": "",
  "license": "MIT",
  "description": "Current AI regulatory landscape — EU AI Act, FINRA, FDA, US state AI laws — and client-system exposure mapping",
  "category": "general",
  "download_status": "downloaded",
  "download_note": "cached",
  "metadata": {
    "subcategory": "legal-compliance",
    "featured": false
  },
  "collected_at": "2026-05-27T03:41:44+00:00"
}
