{
  "name": "clerk-webhooks-events",
  "slug": "clerk-webhooks-events",
  "source": "claudskills",
  "source_url": "https://claudskills.com/skills/clerk-webhooks-events/",
  "download_url": "https://claudskills.com/skills/clerk-webhooks-events/SKILL.md",
  "external_source_url": "",
  "license": "MIT",
  "description": "Configure Clerk webhooks and handle authentication events. Use when setting up user sync, handling auth events, or integrating Clerk with external systems via Svix webhooks. Trigger with phrases like \"clerk webhooks\", \"clerk events\", \"clerk user sync\", \"clerk svix\", \"clerk event handling\".",
  "category": "general",
  "download_status": "downloaded",
  "download_note": "cached",
  "metadata": {
    "subcategory": "hello-world-templates",
    "featured": false
  },
  "collected_at": "2026-05-27T03:42:17+00:00"
}
