{
  "name": "detecting-cloud-threats-with-guardduty",
  "slug": "detecting-cloud-threats-with-guardduty",
  "source": "claudskills",
  "source_url": "https://claudskills.com/skills/detecting-cloud-threats-with-guardduty/",
  "download_url": "https://claudskills.com/skills/detecting-cloud-threats-with-guardduty/SKILL.md",
  "external_source_url": "",
  "license": "Apache-2.0",
  "description": "This skill teaches security teams how to deploy and operationalize Amazon GuardDuty for continuous threat detection",
  "category": "security",
  "download_status": "downloaded",
  "download_note": "cached",
  "metadata": {
    "subcategory": "cloud-security",
    "featured": false
  },
  "collected_at": "2026-05-27T03:42:40+00:00"
}
