{
  "name": "author-skill",
  "slug": "author-skill",
  "source": "claudskills",
  "source_url": "https://claudskills.com/skills/author-skill/",
  "download_url": "https://claudskills.com/skills/author-skill/SKILL.md",
  "external_source_url": "",
  "license": "",
  "description": "Author a new Cody skill and ship it end-to-end. Writes skills/<name>/SKILL.md, commits on the secret-agent-skills-bank branch (Cody's own branch), and fast-forwards main to the same commit so the existing publish-gateway-bundle workflow rebundles skills/** and pulls them onto the gateway. No human review step. Use when the user asks Cody to create a new skill. Do NOT use to edit an existing skill.",
  "category": "security",
  "download_status": "downloaded",
  "download_note": "cached",
  "metadata": {
    "subcategory": "security-misc",
    "featured": false
  },
  "collected_at": "2026-05-27T03:41:57+00:00"
}
