{
  "name": "gitops-audit",
  "slug": "gitops-audit",
  "source": "claudskills",
  "source_url": "https://claudskills.com/skills/gitops-audit/",
  "download_url": "https://claudskills.com/skills/gitops-audit/SKILL.md",
  "external_source_url": "",
  "license": "",
  "description": "Comprehensive GitOps compliance verification that detects configuration drift and policy violations through three audit types - (1) Cluster Drift (resources in cluster not tracked in git), (2) Spec Drift (differences between git manifests and cluster state), (3) Code Violations (hardcoded Kubernetes configs in application code). Automatically triggered when code review detects changes to *.yaml/*.yml in charts/, manifests/, k8s/, kubernetes/, deployment scripts, Helm charts, Kustomize files, or Kubernetes client library imports. Use manually for investigating cluster drift, auditing GitOps compliance, before production deployments, troubleshooting sync issues, or regular compliance checks.",
  "category": "engineering",
  "download_status": "downloaded",
  "download_note": "cached",
  "metadata": {
    "subcategory": "devops",
    "featured": false
  },
  "collected_at": "2026-05-27T03:43:07+00:00"
}
