{
  "name": "wrangler",
  "slug": "wrangler",
  "source": "claudskills",
  "source_url": "https://claudskills.com/skills/wrangler/",
  "download_url": "https://claudskills.com/skills/wrangler/SKILL.md",
  "external_source_url": "",
  "license": "",
  "description": "Cloudflare Workers CLI for deploying, developing, and managing Workers, KV, R2, D1, Vectorize, Hyperdrive, Workers AI, Containers, Queues, Workflows, Pipelines, and Secrets Store. Load before running wrangler commands to ensure correct syntax and best practices.",
  "category": "engineering",
  "download_status": "downloaded",
  "download_note": "cached",
  "metadata": {
    "subcategory": "engineering-misc",
    "featured": false
  },
  "collected_at": "2026-05-27T03:44:37+00:00"
}
