{
  "name": "source-analysis",
  "slug": "source-analysis",
  "source": "claudskills",
  "source_url": "https://claudskills.com/skills/source-analysis/",
  "download_url": "https://claudskills.com/skills/source-analysis/SKILL.md",
  "external_source_url": "",
  "license": "",
  "description": "Primary and secondary source analysis for historical reasoning. Covers source classification, sourcing (author/context/purpose), corroboration across multiple sources, contextualization within time and place, and bias detection. Use when evaluating historical evidence, assessing source reliability, or constructing evidence-based historical arguments.",
  "category": "general",
  "download_status": "downloaded",
  "download_note": "cached",
  "metadata": {
    "subcategory": "general-misc",
    "featured": false
  },
  "collected_at": "2026-05-27T03:44:20+00:00"
}
