{
  "name": "ln-511-code-quality-checker",
  "slug": "ln-511-code-quality-checker",
  "source": "claudskills",
  "source_url": "https://claudskills.com/skills/ln-511-code-quality-checker/",
  "download_url": "https://claudskills.com/skills/ln-511-code-quality-checker/SKILL.md",
  "external_source_url": "",
  "license": "MIT",
  "description": "Checks DRY/KISS/YAGNI/architecture compliance with quantitative Code Quality Score. Use when implementation tasks are Done and need quality scoring.",
  "category": "engineering",
  "download_status": "downloaded",
  "download_note": "cached",
  "metadata": {
    "subcategory": "code-quality",
    "featured": false
  },
  "collected_at": "2026-05-27T03:43:33+00:00"
}
