{
  "name": "nist-pf-identify",
  "slug": "nist-pf-identify",
  "source": "claudskills",
  "source_url": "https://claudskills.com/skills/nist-pf-identify/",
  "download_url": "https://claudskills.com/skills/nist-pf-identify/SKILL.md",
  "external_source_url": "",
  "license": "MIT",
  "description": "Implement the NIST Privacy Framework IDENTIFY function including ID.BE business environment, ID.DA data actions, ID.IM improvement, and ID.RA risk assessment subcategories. Provides control mapping, gap analysis templates, and implementation workflows for privacy risk identification.",
  "category": "general",
  "download_status": "downloaded",
  "download_note": "cached",
  "metadata": {
    "subcategory": "orchestration-frameworks",
    "featured": false
  },
  "collected_at": "2026-05-27T03:43:43+00:00"
}
