{
  "name": "game-monetization",
  "slug": "game-monetization",
  "source": "claudskills",
  "source_url": "https://claudskills.com/skills/game-monetization/",
  "download_url": "https://claudskills.com/skills/game-monetization/SKILL.md",
  "external_source_url": "",
  "license": "",
  "description": "Analyze game monetization implementations including IAP purchase flow and server-side receipt validation, ad mediation waterfall and rewarded video placement, subscription lifecycle and grace period handling, battle pass XP progression, loot box probability disclosure for regulatory compliance, regional pricing tiers, COPPA and GDPR consent, refund revocation, anti-predatory pattern detection, and revenue conversion optimization.",
  "category": "growth",
  "download_status": "downloaded",
  "download_note": "cached",
  "metadata": {
    "subcategory": "conversion",
    "featured": false
  },
  "collected_at": "2026-05-27T03:43:03+00:00"
}
