{
  "name": "guardrails",
  "slug": "guardrails",
  "source": "claudskills",
  "source_url": "https://claudskills.com/skills/guardrails/",
  "download_url": "https://claudskills.com/skills/guardrails/SKILL.md",
  "external_source_url": "",
  "license": "MIT",
  "description": "Security techniques and quality control for prompts and agents",
  "category": "security",
  "download_status": "downloaded",
  "download_note": "cached",
  "metadata": {
    "subcategory": "security-misc",
    "featured": false
  },
  "collected_at": "2026-05-27T03:43:11+00:00"
}
