{
  "name": "azure-kubernetes",
  "slug": "azure-kubernetes",
  "source": "claudskills",
  "source_url": "https://claudskills.com/skills/azure-kubernetes/",
  "download_url": "https://claudskills.com/skills/azure-kubernetes/SKILL.md",
  "external_source_url": "",
  "license": "MIT",
  "description": "Plan, create, and configure production-ready Azure Kubernetes Service (AKS) clusters. Covers Day-0 checklist, SKU selection (Automatic vs Standard), networking options (private API server, Azure CNI Overlay, egress configuration), security, and operations (autoscaling, upgrade strategy, cost analysis). WHEN: create AKS environment, provision AKS environment, enable AKS observability, design AKS networking, choose AKS SKU, secure AKS.",
  "category": "engineering",
  "download_status": "downloaded",
  "download_note": "cached",
  "metadata": {
    "subcategory": "devops",
    "featured": false
  },
  "collected_at": "2026-05-27T03:42:01+00:00"
}
