{
  "name": "gtasks-todo-manager",
  "slug": "gtasks-todo-manager",
  "source": "claudskills",
  "source_url": "https://claudskills.com/skills/gtasks-todo-manager/",
  "download_url": "https://claudskills.com/skills/gtasks-todo-manager/SKILL.md",
  "external_source_url": "",
  "license": "",
  "description": "Manages to-do items across multiple Google accounts using the Google Tasks API. Use when the user needs to create, update, complete, or organize tasks in Google Tasks, manage task lists, or view tasks across multiple Google accounts. Supports personal Gmail, Google Workspace, and organization-provisioned accounts with secure OAuth authentication.",
  "category": "general",
  "download_status": "downloaded",
  "download_note": "cached",
  "metadata": {
    "subcategory": "personal-productivity",
    "featured": false
  },
  "collected_at": "2026-05-27T03:43:11+00:00"
}
