{
  "name": "azure-resource-visualizer",
  "slug": "azure-resource-visualizer",
  "source": "claudskills",
  "source_url": "https://claudskills.com/skills/azure-resource-visualizer/",
  "download_url": "https://claudskills.com/skills/azure-resource-visualizer/SKILL.md",
  "external_source_url": "",
  "license": "",
  "description": "Analyze Azure resource groups and generate detailed Mermaid architecture diagrams showing the relationships between individual resources. USE FOR: create architecture diagram, visualize Azure resources, show resource relationships, generate Mermaid diagram, analyze resource group, diagram my resources, architecture visualization, resource topology, map Azure infrastructure DO NOT USE FOR: creating/modifying resources (use azure-deploy), security scanning (use azure-security), performance troubleshooting (use azure-diagnostics), code generation (use relevant service skill)",
  "category": "engineering",
  "download_status": "downloaded",
  "download_note": "cached",
  "metadata": {
    "subcategory": "cloud-platforms",
    "featured": false
  },
  "collected_at": "2026-05-27T03:42:01+00:00"
}
