{
  "name": "hubspot-enterprise-rbac",
  "slug": "hubspot-enterprise-rbac",
  "source": "claudskills",
  "source_url": "https://claudskills.com/skills/hubspot-enterprise-rbac/",
  "download_url": "https://claudskills.com/skills/hubspot-enterprise-rbac/SKILL.md",
  "external_source_url": "",
  "license": "MIT",
  "description": "Configure HubSpot enterprise access control with OAuth scopes and team permissions. Use when implementing role-based access, configuring per-team HubSpot scopes, or setting up multi-user access patterns for HubSpot integrations. Trigger with phrases like \"hubspot RBAC\", \"hubspot roles\", \"hubspot enterprise\", \"hubspot permissions\", \"hubspot team access\", \"hubspot OAuth scopes\".",
  "category": "sales",
  "download_status": "downloaded",
  "download_note": "cached",
  "metadata": {
    "subcategory": "crm-systems",
    "featured": false
  },
  "collected_at": "2026-05-27T03:43:15+00:00"
}
