{
  "name": "mobile-analytics",
  "slug": "mobile-analytics",
  "source": "claudskills",
  "source_url": "https://claudskills.com/skills/mobile-analytics/",
  "download_url": "https://claudskills.com/skills/mobile-analytics/SKILL.md",
  "external_source_url": "",
  "license": "",
  "description": "Analyze mobile app analytics implementation including event tracking completeness and naming conventions, SDK configuration audit (Firebase Analytics, Amplitude, Mixpanel, PostHog), attribution tracking with AppsFlyer/Adjust/Branch and SKAdNetwork conversion values, funnel analysis readiness for onboarding and conversion flows, crash monitoring setup (Crashlytics, Sentry) with symbolication and alerting, feature flag evaluation logging, retention cohort signal detection, and privacy compliance verification for App Tracking Transparency (ATT), GDPR consent, App Privacy Nutrition Labels, and Play Store Data Safety forms.",
  "category": "growth",
  "download_status": "downloaded",
  "download_note": "cached",
  "metadata": {
    "subcategory": "conversion",
    "featured": false
  },
  "collected_at": "2026-05-27T03:43:39+00:00"
}
